{"nodes": [{"id": "src_core_capture_capturecoordinatorruntime_cpp", "label": "CaptureCoordinatorRuntime.cpp", "file_type": "code", "source_file": "src\\core\\capture\\CaptureCoordinatorRuntime.cpp", "source_location": "L1"}, {"id": "capturecoordinatorruntime_nexteventsequenceids", "label": "nextEventSequenceIds()", "file_type": "code", "source_file": "src\\core\\capture\\CaptureCoordinatorRuntime.cpp", "source_location": "L22"}, {"id": "capturecoordinatorruntime_snapshotsymbolstring", "label": "snapshotSymbolString()", "file_type": "code", "source_file": "src\\core\\capture\\CaptureCoordinatorRuntime.cpp", "source_location": "L30"}, {"id": "capturecoordinatorruntime_maketraderow", "label": "makeTradeRow()", "file_type": "code", "source_file": "src\\core\\capture\\CaptureCoordinatorRuntime.cpp", "source_location": "L34"}, {"id": "capturecoordinatorruntime_makebooktickerrow", "label": "makeBookTickerRow()", "file_type": "code", "source_file": "src\\core\\capture\\CaptureCoordinatorRuntime.cpp", "source_location": "L46"}, {"id": "capturecoordinatorruntime_makepricepairs", "label": "makePricePairs()", "file_type": "code", "source_file": "src\\core\\capture\\CaptureCoordinatorRuntime.cpp", "source_location": "L59"}, {"id": "capturecoordinatorruntime_makedepthrow", "label": "makeDepthRow()", "file_type": "code", "source_file": "src\\core\\capture\\CaptureCoordinatorRuntime.cpp", "source_location": "L68"}, {"id": "capturecoordinatorruntime_makesnapshotdocument", "label": "makeSnapshotDocument()", "file_type": "code", "source_file": "src\\core\\capture\\CaptureCoordinatorRuntime.cpp", "source_location": "L81"}, {"id": "capturecoordinatorruntime_starttrades", "label": "startTrades()", "file_type": "code", "source_file": "src\\core\\capture\\CaptureCoordinatorRuntime.cpp", "source_location": "L106"}, {"id": "capturecoordinatorruntime_stoptrades", "label": "stopTrades()", "file_type": "code", "source_file": "src\\core\\capture\\CaptureCoordinatorRuntime.cpp", "source_location": "L288"}, {"id": "capturecoordinatorruntime_startbookticker", "label": "startBookTicker()", "file_type": "code", "source_file": "src\\core\\capture\\CaptureCoordinatorRuntime.cpp", "source_location": "L297"}, {"id": "capturecoordinatorruntime_stopbookticker", "label": "stopBookTicker()", "file_type": "code", "source_file": "src\\core\\capture\\CaptureCoordinatorRuntime.cpp", "source_location": "L406"}, {"id": "capturecoordinatorruntime_startorderbook", "label": "startOrderbook()", "file_type": "code", "source_file": "src\\core\\capture\\CaptureCoordinatorRuntime.cpp", "source_location": "L415"}, {"id": "capturecoordinatorruntime_stoporderbook", "label": "stopOrderbook()", "file_type": "code", "source_file": "src\\core\\capture\\CaptureCoordinatorRuntime.cpp", "source_location": "L547"}, {"id": "capturecoordinatorruntime_writesnapshotfile", "label": "writeSnapshotFile()", "file_type": "code", "source_file": "src\\core\\capture\\CaptureCoordinatorRuntime.cpp", "source_location": "L556"}], "edges": [{"source": "src_core_capture_capturecoordinatorruntime_cpp", "target": "capturecoordinator", "relation": "imports", "confidence": "EXTRACTED", "source_file": "src\\core\\capture\\CaptureCoordinatorRuntime.cpp", "source_location": "L1", "weight": 1.0}, {"source": "src_core_capture_capturecoordinatorruntime_cpp", "target": "algorithm", "relation": "imports", "confidence": "EXTRACTED", "source_file": "src\\core\\capture\\CaptureCoordinatorRuntime.cpp", "source_location": "L3", "weight": 1.0}, {"source": "src_core_capture_capturecoordinatorruntime_cpp", "target": "cstdio", "relation": "imports", "confidence": "EXTRACTED", "source_file": "src\\core\\capture\\CaptureCoordinatorRuntime.cpp", "source_location": "L4", "weight": 1.0}, {"source": "src_core_capture_capturecoordinatorruntime_cpp", "target": "fstream", "relation": "imports", "confidence": "EXTRACTED", "source_file": "src\\core\\capture\\CaptureCoordinatorRuntime.cpp", "source_location": "L5", "weight": 1.0}, {"source": "src_core_capture_capturecoordinatorruntime_cpp", "target": "string", "relation": "imports", "confidence": "EXTRACTED", "source_file": "src\\core\\capture\\CaptureCoordinatorRuntime.cpp", "source_location": "L6", "weight": 1.0}, {"source": "src_core_capture_capturecoordinatorruntime_cpp", "target": "thread", "relation": "imports", "confidence": "EXTRACTED", "source_file": "src\\core\\capture\\CaptureCoordinatorRuntime.cpp", "source_location": "L7", "weight": 1.0}, {"source": "src_core_capture_capturecoordinatorruntime_cpp", "target": "runbyconfig", "relation": "imports", "confidence": "EXTRACTED", "source_file": "src\\core\\capture\\CaptureCoordinatorRuntime.cpp", "source_location": "L10", "weight": 1.0}, {"source": "src_core_capture_capturecoordinatorruntime_cpp", "target": "getobject", "relation": "imports", "confidence": "EXTRACTED", "source_file": "src\\core\\capture\\CaptureCoordinatorRuntime.cpp", "source_location": "L11", "weight": 1.0}, {"source": "src_core_capture_capturecoordinatorruntime_cpp", "target": "capturecoordinatorinternal", "relation": "imports", "confidence": "EXTRACTED", "source_file": "src\\core\\capture\\CaptureCoordinatorRuntime.cpp", "source_location": "L12", "weight": 1.0}, {"source": "src_core_capture_capturecoordinatorruntime_cpp", "target": "jsonserializers", "relation": "imports", "confidence": "EXTRACTED", "source_file": "src\\core\\capture\\CaptureCoordinatorRuntime.cpp", "source_location": "L13", "weight": 1.0}, {"source": "src_core_capture_capturecoordinatorruntime_cpp", "target": "cxetcapturebridge", "relation": "imports", "confidence": "EXTRACTED", "source_file": "src\\core\\capture\\CaptureCoordinatorRuntime.cpp", "source_location": "L14", "weight": 1.0}, {"source": "src_core_capture_capturecoordinatorruntime_cpp", "target": "localorderengine", "relation": "imports", "confidence": "EXTRACTED", "source_file": "src\\core\\capture\\CaptureCoordinatorRuntime.cpp", "source_location": "L15", "weight": 1.0}, {"source": "src_core_capture_capturecoordinatorruntime_cpp", "target": "metrics", "relation": "imports", "confidence": "EXTRACTED", "source_file": "src\\core\\capture\\CaptureCoordinatorRuntime.cpp", "source_location": "L16", "weight": 1.0}, {"source": "src_core_capture_capturecoordinatorruntime_cpp", "target": "capturecoordinatorruntime_nexteventsequenceids", "relation": "contains", "confidence": "EXTRACTED", "source_file": "src\\core\\capture\\CaptureCoordinatorRuntime.cpp", "source_location": "L22", "weight": 1.0}, {"source": "src_core_capture_capturecoordinatorruntime_cpp", "target": "capturecoordinatorruntime_snapshotsymbolstring", "relation": "contains", "confidence": "EXTRACTED", "source_file": "src\\core\\capture\\CaptureCoordinatorRuntime.cpp", "source_location": "L30", "weight": 1.0}, {"source": "src_core_capture_capturecoordinatorruntime_cpp", "target": "capturecoordinatorruntime_maketraderow", "relation": "contains", "confidence": "EXTRACTED", "source_file": "src\\core\\capture\\CaptureCoordinatorRuntime.cpp", "source_location": "L34", "weight": 1.0}, {"source": "src_core_capture_capturecoordinatorruntime_cpp", "target": "capturecoordinatorruntime_makebooktickerrow", "relation": "contains", "confidence": "EXTRACTED", "source_file": "src\\core\\capture\\CaptureCoordinatorRuntime.cpp", "source_location": "L46", "weight": 1.0}, {"source": "src_core_capture_capturecoordinatorruntime_cpp", "target": "capturecoordinatorruntime_makepricepairs", "relation": "contains", "confidence": "EXTRACTED", "source_file": "src\\core\\capture\\CaptureCoordinatorRuntime.cpp", "source_location": "L59", "weight": 1.0}, {"source": "src_core_capture_capturecoordinatorruntime_cpp", "target": "capturecoordinatorruntime_makedepthrow", "relation": "contains", "confidence": "EXTRACTED", "source_file": "src\\core\\capture\\CaptureCoordinatorRuntime.cpp", "source_location": "L68", "weight": 1.0}, {"source": "src_core_capture_capturecoordinatorruntime_cpp", "target": "capturecoordinatorruntime_makesnapshotdocument", "relation": "contains", "confidence": "EXTRACTED", "source_file": "src\\core\\capture\\CaptureCoordinatorRuntime.cpp", "source_location": "L81", "weight": 1.0}, {"source": "src_core_capture_capturecoordinatorruntime_cpp", "target": "capturecoordinatorruntime_starttrades", "relation": "contains", "confidence": "EXTRACTED", "source_file": "src\\core\\capture\\CaptureCoordinatorRuntime.cpp", "source_location": "L106", "weight": 1.0}, {"source": "src_core_capture_capturecoordinatorruntime_cpp", "target": "capturecoordinatorruntime_stoptrades", "relation": "contains", "confidence": "EXTRACTED", "source_file": "src\\core\\capture\\CaptureCoordinatorRuntime.cpp", "source_location": "L288", "weight": 1.0}, {"source": "src_core_capture_capturecoordinatorruntime_cpp", "target": "capturecoordinatorruntime_startbookticker", "relation": "contains", "confidence": "EXTRACTED", "source_file": "src\\core\\capture\\CaptureCoordinatorRuntime.cpp", "source_location": "L297", "weight": 1.0}, {"source": "src_core_capture_capturecoordinatorruntime_cpp", "target": "capturecoordinatorruntime_stopbookticker", "relation": "contains", "confidence": "EXTRACTED", "source_file": "src\\core\\capture\\CaptureCoordinatorRuntime.cpp", "source_location": "L406", "weight": 1.0}, {"source": "src_core_capture_capturecoordinatorruntime_cpp", "target": "capturecoordinatorruntime_startorderbook", "relation": "contains", "confidence": "EXTRACTED", "source_file": "src\\core\\capture\\CaptureCoordinatorRuntime.cpp", "source_location": "L415", "weight": 1.0}, {"source": "src_core_capture_capturecoordinatorruntime_cpp", "target": "capturecoordinatorruntime_stoporderbook", "relation": "contains", "confidence": "EXTRACTED", "source_file": "src\\core\\capture\\CaptureCoordinatorRuntime.cpp", "source_location": "L547", "weight": 1.0}, {"source": "src_core_capture_capturecoordinatorruntime_cpp", "target": "capturecoordinatorruntime_writesnapshotfile", "relation": "contains", "confidence": "EXTRACTED", "source_file": "src\\core\\capture\\CaptureCoordinatorRuntime.cpp", "source_location": "L556", "weight": 1.0}, {"source": "capturecoordinatorruntime_makedepthrow", "target": "capturecoordinatorruntime_makepricepairs", "relation": "calls", "confidence": "EXTRACTED", "source_file": "src\\core\\capture\\CaptureCoordinatorRuntime.cpp", "source_location": "L76", "weight": 1.0}, {"source": "capturecoordinatorruntime_makesnapshotdocument", "target": "capturecoordinatorruntime_makepricepairs", "relation": "calls", "confidence": "EXTRACTED", "source_file": "src\\core\\capture\\CaptureCoordinatorRuntime.cpp", "source_location": "L99", "weight": 1.0}, {"source": "capturecoordinatorruntime_starttrades", "target": "capturecoordinatorruntime_nexteventsequenceids", "relation": "calls", "confidence": "EXTRACTED", "source_file": "src\\core\\capture\\CaptureCoordinatorRuntime.cpp", "source_location": "L223", "weight": 1.0}, {"source": "capturecoordinatorruntime_starttrades", "target": "capturecoordinatorruntime_maketraderow", "relation": "calls", "confidence": "EXTRACTED", "source_file": "src\\core\\capture\\CaptureCoordinatorRuntime.cpp", "source_location": "L226", "weight": 1.0}, {"source": "capturecoordinatorruntime_startbookticker", "target": "capturecoordinatorruntime_nexteventsequenceids", "relation": "calls", "confidence": "EXTRACTED", "source_file": "src\\core\\capture\\CaptureCoordinatorRuntime.cpp", "source_location": "L360", "weight": 1.0}, {"source": "capturecoordinatorruntime_startbookticker", "target": "capturecoordinatorruntime_makebooktickerrow", "relation": "calls", "confidence": "EXTRACTED", "source_file": "src\\core\\capture\\CaptureCoordinatorRuntime.cpp", "source_location": "L363", "weight": 1.0}, {"source": "capturecoordinatorruntime_startorderbook", "target": "capturecoordinatorruntime_writesnapshotfile", "relation": "calls", "confidence": "EXTRACTED", "source_file": "src\\core\\capture\\CaptureCoordinatorRuntime.cpp", "source_location": "L481", "weight": 1.0}, {"source": "capturecoordinatorruntime_startorderbook", "target": "capturecoordinatorruntime_nexteventsequenceids", "relation": "calls", "confidence": "EXTRACTED", "source_file": "src\\core\\capture\\CaptureCoordinatorRuntime.cpp", "source_location": "L507", "weight": 1.0}, {"source": "capturecoordinatorruntime_startorderbook", "target": "capturecoordinatorruntime_makedepthrow", "relation": "calls", "confidence": "EXTRACTED", "source_file": "src\\core\\capture\\CaptureCoordinatorRuntime.cpp", "source_location": "L509", "weight": 1.0}, {"source": "capturecoordinatorruntime_writesnapshotfile", "target": "capturecoordinatorruntime_nexteventsequenceids", "relation": "calls", "confidence": "EXTRACTED", "source_file": "src\\core\\capture\\CaptureCoordinatorRuntime.cpp", "source_location": "L575", "weight": 1.0}, {"source": "capturecoordinatorruntime_writesnapshotfile", "target": "capturecoordinatorruntime_snapshotsymbolstring", "relation": "calls", "confidence": "EXTRACTED", "source_file": "src\\core\\capture\\CaptureCoordinatorRuntime.cpp", "source_location": "L580", "weight": 1.0}, {"source": "capturecoordinatorruntime_writesnapshotfile", "target": "capturecoordinatorruntime_makesnapshotdocument", "relation": "calls", "confidence": "EXTRACTED", "source_file": "src\\core\\capture\\CaptureCoordinatorRuntime.cpp", "source_location": "L587", "weight": 1.0}]}